vesta/__init__.py
vesta/chars.py
vesta/clients.py
vesta/http.py
vesta/py.typed
vesta/vbml.py
vesta-0.13.0.dist-info/licenses/LICENSE
vesta-0.13.0.dist-info/METADATA
vesta-0.13.0.dist-info/WHEEL
vesta-0.13.0.dist-info/top_level.txt
vesta-0.13.0.dist-info/RECORD
