Metadata-Version: 2.4
Name: vesta
Version: 0.13.0
Summary: Vestaboard client library
Author-email: Jon Parise <jon@indelible.org>
License-Expression: MIT
Project-URL: Homepage, https://github.com/jparise/vesta
Project-URL: Documentation, https://vesta-py.readthedocs.io/
Project-URL: Repository, https://github.com/jparise/vesta.git
Project-URL: Issues, https://github.com/jparise/vesta/issues
Project-URL: Changelog, https://github.com/jparise/vesta/blob/main/CHANGELOG.md
Keywords: vestaboard
Classifier: Development Status :: 4 - Beta
Classifier: Programming Language :: Python
Classifier: Programming Language :: Python :: 3 :: Only
Classifier: Programming Language :: Python :: 3.10
Classifier: Programming Language :: Python :: 3.11
Classifier: Programming Language :: Python :: 3.12
Classifier: Programming Language :: Python :: 3.13
Classifier: Programming Language :: Python :: 3.14
Requires-Python: >=3.10
License-File: LICENSE
Dynamic: license-file
